piecash/__init__.py
piecash/_common.py
piecash/_declbase.py
piecash/budget.py
piecash/kvp.py
piecash/ledger.py
piecash/metadata.py
piecash/sa_extra.py
piecash/business/__init__.py
piecash/business/invoice.py
piecash/business/person.py
piecash/business/tax.py
piecash/core/__init__.py
piecash/core/_commodity_helper.py
piecash/core/account.py
piecash/core/book.py
piecash/core/commodity.py
piecash/core/currency_ISO.py
piecash/core/factories.py
piecash/core/session.py
piecash/core/transaction.py
piecash-0.13.0.data/scripts/piecash_ledger.py
piecash-0.13.0.data/scripts/piecash_prices.py
piecash-0.13.0.data/scripts/piecash_toqif.py
piecash-0.13.0.dist-info/DESCRIPTION.rst
piecash-0.13.0.dist-info/METADATA
piecash-0.13.0.dist-info/RECORD
piecash-0.13.0.dist-info/WHEEL
piecash-0.13.0.dist-info/metadata.json
piecash-0.13.0.dist-info/top_level.txt
