Metadata-Version: 2.0
Name: piecash
Version: 0.13.0
Summary: A pythonic interface to GnuCash SQL documents.
Home-page: https://github.com/sdementen/piecash
Author: sdementen
Author-email: sdementen@gmail.com
License: MIT
Keywords: GnuCash,python,binding,interface,sqlalchemy
Platform: any
Classifier: Development Status :: 4 - Beta
Classifier: Environment :: Console
Classifier: Intended Audience :: Developers
Classifier: Intended Audience :: Financial and Insurance Industry
Classifier: License :: OSI Approved :: MIT License
Classifier: Natural Language :: English
Classifier: Operating System :: OS Independent
Classifier: Programming Language :: Python :: 2.7
Classifier: Programming Language :: Python :: 3.4
Classifier: Programming Language :: Python :: 3.5
Classifier: Programming Language :: Python :: 3.6
Classifier: Topic :: Office/Business
Classifier: Topic :: Office/Business :: Financial
Classifier: Topic :: Office/Business :: Financial :: Accounting
Classifier: Topic :: Software Development :: Libraries :: Python Modules
Requires-Dist: SQLAlchemy (>=1.0)
Requires-Dist: SQLAlchemy-Utils (>=0.31)
Requires-Dist: enum-compat
Requires-Dist: pytz
Requires-Dist: tzlocal
Requires-Dist: yahoo-finance
